asct_parser/__init__.py
asct_parser/__main__.py
asct_parser/asct_parser.py
asct_parser/utils/__init__.py
asct_parser/utils/util.py
asct_parser-0.1.0.dist-info/LICENSE
asct_parser-0.1.0.dist-info/METADATA
asct_parser-0.1.0.dist-info/WHEEL
asct_parser-0.1.0.dist-info/entry_points.txt
asct_parser-0.1.0.dist-info/RECORD
