Metadata-Version: 2.1
Name: asct-parser
Version: 0.1.0
Summary: Parse ASCT+B tables into two columns (+ label columns).
License: http://www.apache.org/licenses/LICENSE-2.0
Author: Anita Caron
Author-email: anitacaron@users.noreply.github.com
Requires-Python: >=3.9,<4.0
Classifier: License :: Other/Proprietary License
Classifier: Programming Language :: Python :: 3
Classifier: Programming Language :: Python :: 3.9
Classifier: Programming Language :: Python :: 3.10
Classifier: Programming Language :: Python :: 3.11
Requires-Dist: pandas (>=2.2.0,<3.0.0)
Requires-Dist: requests (>=2.31.0,<3.0.0)
